subseq_tamil/__init__.py
subseq_tamil/rough py2.py
subseq_tamil/subsequence.py
subseq_tamil-0.1.6.dist-info/LICENSE.txt
subseq_tamil-0.1.6.dist-info/METADATA
subseq_tamil-0.1.6.dist-info/WHEEL
subseq_tamil-0.1.6.dist-info/top_level.txt
subseq_tamil-0.1.6.dist-info/RECORD
