Metadata-Version: 2.1
Name: subseq_tamil
Version: 0.1.6
Summary: A brief description of your package
Home-page: https://github.com/yourusername/subseq_tamil
Author: Your Name
Author-email: your_email@example.com
Classifier: Programming Language :: Python :: 3
Classifier: License :: OSI Approved :: MIT License
Classifier: Operating System :: OS Independent
Requires-Python: >=3.6
License-File: LICENSE.txt
